compaipair/__init__.py
compaipair/cli.py
compaipair/complete/__init__.py
compaipair/complete/cli_functions.py
compaipair/complete/commands.py
compaipair/config/__init__.py
compaipair/config/cli_functions.py
compaipair/config/commands.py
compaipair/main.py
compaipair/templates/__init__.py
compaipair/templates/cli_functions.py
compaipair/templates/commands.py
compaipair/types/__init__.py
compaipair/types/compaicompletion.py
compaipair/types/completion_template.py
compaipair/types/exceptions.py
compaipair/utils.py
compaipair-0.4.6.dist-info/LICENSE
compaipair-0.4.6.dist-info/METADATA
compaipair-0.4.6.dist-info/WHEEL
compaipair-0.4.6.dist-info/entry_points.txt
compaipair-0.4.6.dist-info/RECORD
